palewire/__init__.py
palewire/about.html
palewire/layout.html
palewire/nav.html
palewire/navigation.html
palewire/support.py
palewire/theme.conf
palewire/static/custom.css
palewire/static/palewire.css_t
sphinx_palewire_theme-0.0.3.dist-info/LICENSE
sphinx_palewire_theme-0.0.3.dist-info/METADATA
sphinx_palewire_theme-0.0.3.dist-info/WHEEL
sphinx_palewire_theme-0.0.3.dist-info/entry_points.txt
sphinx_palewire_theme-0.0.3.dist-info/top_level.txt
sphinx_palewire_theme-0.0.3.dist-info/RECORD
